cryptoapis/__init__.py
cryptoapis/api_client.py
cryptoapis/configuration.py
cryptoapis/exceptions.py
cryptoapis/model_utils.py
cryptoapis/rest.py
cryptoapis/api/__init__.py
cryptoapis/api/assets_api.py
cryptoapis/api/automatic_coins_forwarding_api.py
cryptoapis/api/automatic_tokens_forwarding_api.py
cryptoapis/api/create_subscriptions_for_api.py
cryptoapis/api/default_api.py
cryptoapis/api/exchange_rates_api.py
cryptoapis/api/manage_subscriptions_api.py
cryptoapis/api/metadata_api.py
cryptoapis/api/omni_layer_api.py
cryptoapis/api/tokens_api.py
cryptoapis/api/unified_endpoints_api.py
cryptoapis/api/utxo_based_api.py
cryptoapis/api/validating_api.py
cryptoapis/api/xrp__ripple_api.py
cryptoapis/apis/__init__.py
cryptoapis/model/__init__.py
cryptoapis/model/add_tokens_to_existing_from_address_request_body.py
cryptoapis/model/add_tokens_to_existing_from_address_request_body_data.py
cryptoapis/model/add_tokens_to_existing_from_address_request_body_data_item.py
cryptoapis/model/add_tokens_to_existing_from_address_request_body_token_data.py
cryptoapis/model/add_tokens_to_existing_from_address_request_body_token_data_bitcoin_omni_token.py
cryptoapis/model/add_tokens_to_existing_from_address_request_body_token_data_ethereum_erc20_token.py
cryptoapis/model/add_tokens_to_existing_from_address_response.py
cryptoapis/model/add_tokens_to_existing_from_address_response_data.py
cryptoapis/model/add_tokens_to_existing_from_address_response_item.py
cryptoapis/model/add_tokens_to_existing_from_address_response_item_token_data.py
cryptoapis/model/add_tokens_to_existing_from_address_response_item_token_data_bitcoin_omni_token.py
cryptoapis/model/add_tokens_to_existing_from_address_response_item_token_data_ethereum_erc20_token.py
cryptoapis/model/address_coins_transaction_confirmed.py
cryptoapis/model/address_coins_transaction_confirmed_data.py
cryptoapis/model/address_coins_transaction_confirmed_data_item.py
cryptoapis-1.0.0.dist-info/LICENSE.md
cryptoapis-1.0.0.dist-info/METADATA
cryptoapis-1.0.0.dist-info/WHEEL
cryptoapis-1.0.0.dist-info/top_level.txt
cryptoapis-1.0.0.dist-info/RECORD
