Metadata-Version: 2.1
Name: cryptoapis
Version: 1.0.0
Summary: CryptoAPIs Python client
Home-page: https://github.com/Crypto-APIs/Crypto_APIs_2.0_SDK_Python
Author: CryptoAPIs Team
Author-email: developers@cryptoapis.io
License: MIT
Keywords: OpenAPI,OpenAPI-Generator,CryptoAPIs
Platform: UNKNOWN
Requires-Python: >=3.6
Requires-Dist: urllib3 (>=1.25.3)
Requires-Dist: python-dateutil
